SensorModules/__init__.py
SensorModules/modules/__init__.py
SensorModules/modules/dht.py
ag_sensormodules-0.2.dist-info/LICENSE
ag_sensormodules-0.2.dist-info/METADATA
ag_sensormodules-0.2.dist-info/WHEEL
ag_sensormodules-0.2.dist-info/top_level.txt
ag_sensormodules-0.2.dist-info/RECORD
