Metadata-Version: 2.1
Name: ag-sensormodules
Version: 0.2
Summary: Sensor Modules for Our Thesis
Home-page: https://gitlab.com/re-thesis/sensor_modules
Author: Joshua Kim Rivera,Kim Sunga
Author-email: joshuakimrivera@gmail.com
License: Type license() to see the full license text
Platform: UNKNOWN
Requires-Dist: nanpy (==0.9.6)
